dinoop_grypescan/__init__.py
dinoop_grypescan/utils.py
dinoop_trivyscan2/__init__.py
dinoop_trivyscan2/utils.py
dinoop_image_scan3-0.1.1.dist-info/METADATA
dinoop_image_scan3-0.1.1.dist-info/WHEEL
dinoop_image_scan3-0.1.1.dist-info/top_level.txt
dinoop_image_scan3-0.1.1.dist-info/RECORD
